tabulate_cell_merger/__init__.py
tabulate_cell_merger/tabulate_cell_merger.py
tabulate_cell_merger-0.0.2.dist-info/LICENSE.txt
tabulate_cell_merger-0.0.2.dist-info/METADATA
tabulate_cell_merger-0.0.2.dist-info/WHEEL
tabulate_cell_merger-0.0.2.dist-info/top_level.txt
tabulate_cell_merger-0.0.2.dist-info/RECORD
